pyroclastic-3.1.4.dist-info/licenses/LICENSE
scripts/add_queries.sh
scripts/arg_parse.sh
scripts/bug_mining.py
scripts/database_types.py
scripts/docker-shell.sh
scripts/find_bug_injection.py
scripts/fninstr.py
scripts/funcs.sh
scripts/generate_schema.py
scripts/get_c_files.py
scripts/inject.py
scripts/lava.py
scripts/lava.sh
scripts/lava.sql
scripts/preprocess.py
scripts/process_compile_commands.py
scripts/reset_db.sh
scripts/setup_postgres.sh
scripts/shell.sh
scripts/sw-btrace
scripts/sw-btrace-to-compiledb
scripts/test_crash.py
scripts/vars.py
scripts/vars.sh
pyroclastic-3.1.4.dist-info/METADATA
pyroclastic-3.1.4.dist-info/WHEEL
pyroclastic-3.1.4.dist-info/top_level.txt
pyroclastic-3.1.4.dist-info/RECORD
