Metadata-Version: 2.4
Name: pyroclastic
Version: 3.1.4
Summary: Python Interface for LAVA
Author-email: Andrew Quijano <andrew.quijano@nyu.edu>
License-Expression: GPL-2.0-only
Project-URL: Homepage, https://github.com/panda-re/lava
Project-URL: Source, https://github.com/panda-re/lava
Project-URL: Tracker, https://github.com/panda-re/lava/issues
Classifier: Programming Language :: Python :: 3
Classifier: Programming Language :: Python :: 3.10
Classifier: Programming Language :: Python :: 3.11
Classifier: Programming Language :: Python :: 3.12
Classifier: Programming Language :: Python :: 3.13
Classifier: Operating System :: OS Independent
Classifier: Intended Audience :: Developers
Classifier: Topic :: Software Development :: Libraries :: Python Modules
Requires-Python: >=3.10
License-File: LICENSE
Requires-Dist: dotenv
Requires-Dist: colorama
Requires-Dist: db
Requires-Dist: ipython
Requires-Dist: lockfile
Requires-Dist: numpy
Requires-Dist: pandare==1.8.78
Requires-Dist: PyYAML
Requires-Dist: SQLAlchemy
Requires-Dist: tabulate
Requires-Dist: psycopg2-binary
Requires-Dist: ijson
Dynamic: license-file
